hyperxql/__init__.py
hyperxql/agent.py
hyperxql/cli.py
hyperxql/config.py
hyperxql/database_analyzer.py
hyperxql/db_analyzer.py
hyperxql/db_manager.py
hyperxql/exceptions.py
hyperxql/llm_client.py
hyperxql/py.typed
hyperxql/query_optimizer.py
hyperxql/schema_visualizer.py
hyperxql/sql_generator.py
hyperxql/utils.py
hyperxql/verify_db.py
hyperxql/version.py
hyperxql-2.0.1.dist-info/licenses/LICENSE
hyperxql-2.0.1.dist-info/METADATA
hyperxql-2.0.1.dist-info/WHEEL
hyperxql-2.0.1.dist-info/entry_points.txt
hyperxql-2.0.1.dist-info/top_level.txt
hyperxql-2.0.1.dist-info/RECORD
