Metadata-Version: 2.4
Name: hyperxql
Version: 2.0.1
Summary: An advanced AI-powered tool that bridges the gap between natural language and database operations, featuring an autonomous database agent and intelligent query generation
Home-page: https://github.com/skandanv/hyperxql
Author: HyperXQL Team
Author-email: hyperxql@skandan.com
License: MIT
Project-URL: Homepage, https://github.com/hyperdyn-ai/hyperxql
Project-URL: Bug Tracker, https://github.com/hyperdyn-ai/hyperxql/issues
Project-URL: Documentation, https://github.com/hyperdyn-ai/hyperxql/wiki
Project-URL: Source Code, https://github.com/hyperdyn-ai/hyperxql
Keywords: database-tools,natural-language-processing,sql-generation,ai-assistant,database-agent,nlp,llm,sqlite,postgresql,mysql,database-management,query-generation
Classifier: Programming Language :: Python :: 3
Classifier: License :: OSI Approved :: MIT License
Classifier: Operating System :: OS Independent
Classifier: Topic :: Database
Classifier: Topic :: Scientific/Engineering :: Artificial Intelligence
Classifier: Topic :: Database :: Front-Ends
Classifier: Topic :: Software Development :: Libraries :: Python Modules
Classifier: Topic :: Utilities
Classifier: Intended Audience :: Developers
Classifier: Intended Audience :: Information Technology
Classifier: Intended Audience :: Science/Research
Classifier: Environment :: Console
Classifier: Environment :: Web Environment
Requires-Python: >=3.8
License-File: LICENSE
Requires-Dist: build>=1.0.3
Requires-Dist: click>=8.1.8
Requires-Dist: python-dotenv>=1.0.1
Requires-Dist: email-validator>=2.2.0
Requires-Dist: flask>=3.1.0
Requires-Dist: flask-sqlalchemy>=3.1.1
Requires-Dist: graphviz>=0.20.3
Requires-Dist: gunicorn>=23.0.0
Requires-Dist: openai>=1.68.2
Requires-Dist: psycopg2-binary>=2.9.10
Requires-Dist: pydot>=3.0.4
Requires-Dist: requests>=2.32.3
Requires-Dist: rich>=13.9.4
Requires-Dist: setuptools>=78.0.2
Requires-Dist: sqlalchemy>=2.0.39
Requires-Dist: together>=1.3.0
Requires-Dist: twine>=6.1.0
Requires-Dist: werkzeug>=3.1.3
Dynamic: author-email
Dynamic: home-page
Dynamic: license-file
Dynamic: requires-python
